{
  "assignee": "",
  "blocked_by": [
    "turnkey-8i7"
  ],
  "blocks": [
    "turnkey-c8o"
  ],
  "closed_at": "2026-01-09T09:42:08.486210397+01:00",
  "close_reason": "Implemented gobuckify integration for BUCK file generation",
  "created": "2026-01-08T20:57:13.627008054+01:00",
  "description": "Create tooling to automatically generate BUCK files for Go libraries in the deps cell.\n\n## Solution: Use gobuckify from Buck2 prelude\n\n[gobuckify](https://buck2.build/docs/users/languages/go/third_party_packages/) is a tool built into Buck2's prelude that automatically generates BUCK files for Go third-party dependencies.\n\n### Implementation Progress\n\n✅ **Patched gobuckify for Nix**: Created `nix/packages/gobuckify.nix` that:\n- Fetches from upstream facebook/buck2 (pinned to 2026-01-02 tag)\n- Applies patch to use `go` directly instead of `buck2 run toolchains//:go[go]`\n- Uses sparse checkout to only fetch gobuckify source\n- Creates go.mod since upstream uses Buck2 (not Go modules)\n\n🔄 **Next: Integrate into go-deps-cell.nix**:\n1. Copy full source trees (not just root *.go)\n2. Create synthetic go.mod for vendored deps\n3. Create gobuckify.json config\n4. Run gobuckify to generate BUCK files\n\n### How gobuckify works\n\n1. Reads `go.mod` and vendored dependencies\n2. Uses `go list all` across multiple goos/goarch combinations\n3. Reads configuration from `gobuckify.json`\n4. Generates BUCK files with platform-aware `go_library` rules\n\n### Configuration (gobuckify.json)\n\n```json\n{\n  \"buck\": {\n    \"Preambule\": \"# Auto-generated by gobuckify\",\n    \"GoLibraryRule\": \"go_library\",\n    \"DepsTargetLabelPrefix\": \"godeps//vendor/\",\n    \"DepsAttr\": \"deps\"\n  },\n  \"platforms\": [\n    {\"go_os\": \"linux\", \"go_arch\": \"amd64\", \"buck_os\": \"linux\", \"buck_arch\": \"x86_64\"},\n    {\"go_os\": \"darwin\", \"go_arch\": \"arm64\", \"buck_os\": \"macos\", \"buck_arch\": \"arm64\"}\n  ]\n}\n```\n\nSee: https://github.com/facebook/buck2/tree/main/prelude/go/tools/gobuckify",
  "id": "turnkey-9ws",
  "labels": [],
  "priority": 2,
  "status": "closed",
  "title": "BUCK file generation for Go libraries",
  "type": "task",
  "updated_at": "2026-03-17T17:25:27Z"
}
